pydistort/__init__.py
pydistort/image/__init__.py
pydistort/image/apng_tools.py
pydistort/image/default.py
pydistort/image/lottie_tools.py
pydistort/image/seam_carving.py
pydistort/image/seam_carving_py.py
pydistort/image/webm_tools.py
pydistort/utils/__init__.py
pydistort/utils/libs.py
pydistort/utils/queue.py
pydistort/utils/runners.py
pydistort/video/__init__.py
pydistort-0.0.2.dist-info/METADATA
pydistort-0.0.2.dist-info/WHEEL
pydistort-0.0.2.dist-info/licenses/LICENSE
pydistort-0.0.2.dist-info/RECORD
