Metadata-Version: 2.1
Name: pydistort
Version: 0.0.2
Summary: Asynchronous media distortion module
Project-URL: Documentation, https://github.com/barsikus007/pydistort#readme
Project-URL: Issues, https://github.com/barsikus007/pydistort/issues
Project-URL: Source, https://github.com/barsikus007/pydistort
Author: barsikus007
License-Expression: MIT
License-File: LICENSE
Keywords: asyncio,distort
Classifier: Development Status :: 4 - Beta
Classifier: Programming Language :: Python
Classifier: Programming Language :: Python :: 3.10
Classifier: Programming Language :: Python :: 3.11
Classifier: Programming Language :: Python :: 3.12
Classifier: Programming Language :: Python :: Implementation :: CPython
Classifier: Programming Language :: Python :: Implementation :: PyPy
Requires-Python: >=3.10
Requires-Dist: pillow~=10.2.0
Provides-Extra: all
Requires-Dist: pydistort[apng,lottie]; extra == 'all'
Provides-Extra: apng
Requires-Dist: apng~=0.3.4; extra == 'apng'
Provides-Extra: lottie
Requires-Dist: lottie[gif]~=0.7.0; extra == 'lottie'
